Metadata-Version: 1.1
Name: mettler-toledo-device
Version: 1.5.0
Summary: Interface to Mettler Toledo balances and scales that use the Mettler Toledo Standard Interface Command Set (MT-SICS).
Home-page: https://github.com/janelia-pypi/mettler_toledo_device_python
Author: Peter Polidoro
Author-email: polidorop@janelia.hhmi.org
License: BSD
Keywords: mettler toledo serial device
Platform: UNKNOWN
Classifier: Development Status :: 4 - Beta
Classifier: Intended Audience :: Developers
Classifier: Topic :: Software Development :: Build Tools
Classifier: License :: OSI Approved :: BSD License
Classifier: Programming Language :: Python :: 2.7
